LICENSE
MANIFEST.in
setup.py
doc/Makefile
doc/examples.py
doc/source/conf.py
doc/source/index.rst
doc/source/intro.rst
dummydata/__init__.py
dummydata/__init__.pyc
dummydata/dummydata.py
dummydata/dummydata.pyc
dummydata/meta.py
dummydata/meta.py.bak
dummydata/meta.pyc
dummydata/model2.py
dummydata/model2.pyc
dummydata/model3.py
dummydata/model3.pyc
dummydata.egg-info/PKG-INFO
dummydata.egg-info/SOURCES.txt
dummydata.egg-info/dependency_links.txt
dummydata.egg-info/requires.txt
dummydata.egg-info/top_level.txt
dummydata/__pycache__/__init__.cpython-36.pyc
dummydata/__pycache__/dummydata.cpython-36.pyc
dummydata/__pycache__/meta.cpython-36.pyc
dummydata/__pycache__/model2.cpython-36.pyc
dummydata/__pycache__/model3.cpython-36.pyc
dummydata/bin/activate
dummydata/bin/conda
dummydata/bin/deactivate
test/test_DummyData.py
test/test_meta.py
test/test_model.py