Metadata-Version: 1.1
Name: dummydata
Version: 0.1.4
Summary: dummydata - package for generation of random daa fields
Home-page: https://github.com/pygeo/dummydata
Author: Alexander Loew
Author-email: alexander.loew@lmu.de
License: APACHE 2.0
Keywords: data,science,climate,meteorology,model evaluation,benchmarking,metrics
Platform: UNKNOWN
Classifier: Programming Language :: Python :: 2.7
